cortex/__init__.py
cortex/config.py
cortex/main.py
cortex/plugins.py
cortex/_lib/__init__.py
cortex/_lib/config.py
cortex/_lib/exp.py
cortex/_lib/handlers.py
cortex/_lib/log_utils.py
cortex/_lib/models.py
cortex/_lib/optimizer.py
cortex/_lib/parsing.py
cortex/_lib/reg.py
cortex/_lib/train.py
cortex/_lib/utils.py
cortex/_lib/viz.py
cortex/_lib/viz_utils.py
cortex/_lib/data/__init__.py
cortex/_lib/data/data_handler.py
cortex/_lib/data/noise.py
cortex/built_ins/__init__.py
cortex/built_ins/datasets/CelebA.py
cortex/built_ins/datasets/__init__.py
cortex/built_ins/datasets/dSprites.py
cortex/built_ins/datasets/imagenet.py
cortex/built_ins/datasets/nii_dataload.py
cortex/built_ins/datasets/torchvision_datasets.py
cortex/built_ins/datasets/toysets.py
cortex/built_ins/datasets/utils.py
cortex/built_ins/models/__init__.py
cortex/built_ins/models/adversarial_autoencoder.py
cortex/built_ins/models/ali.py
cortex/built_ins/models/classifier.py
cortex/built_ins/models/discrete_gan.py
cortex/built_ins/models/gan.py
cortex/built_ins/models/mine.py
cortex/built_ins/models/utils.py
cortex/built_ins/models/vae.py
cortex/built_ins/networks/SpectralNormLayer.py
cortex/built_ins/networks/__init__.py
cortex/built_ins/networks/conv_decoders.py
cortex/built_ins/networks/convnets.py
cortex/built_ins/networks/fully_connected.py
cortex/built_ins/networks/modules.py
cortex/built_ins/networks/resnets.py
cortex/built_ins/networks/tv_models_wrapper.py
cortex/built_ins/networks/utils.py
cortex/built_ins/transforms/__init__.py
cortex/built_ins/transforms/sobel.py
cortex-0.11.dist-info/METADATA
cortex-0.11.dist-info/RECORD
cortex-0.11.dist-info/WHEEL
cortex-0.11.dist-info/entry_points.txt
cortex-0.11.dist-info/top_level.txt
