Metadata-Version: 2.1
Name: cortex
Version: 0.11
Summary: A library for wrapping your pytorch code
Home-page: UNKNOWN
Author: R Devon Hjelm
Author-email: erroneus@gmail.com
License: UNKNOWN
Platform: UNKNOWN
Requires-Dist: imageio
Requires-Dist: matplotlib
Requires-Dist: progressbar2
Requires-Dist: scipy
Requires-Dist: sklearn
Requires-Dist: torchvision
Requires-Dist: visdom
Requires-Dist: pyyaml
